{
  "name": "c-quence",
  "url": "https://www.fliptop.com.ph/emcees/c-quence",
  "profilePicture": "https://www.fliptop.com.ph/storage/emcees/April2022/NRwSBjIuINmeeIbMRbdD.jpg",
  "title": "Emcee: C-Quence | FlipTop Battle League",
  "hometown": "Dasmarinas, Cavite",
  "reppin": "Manipesto, Poetic Mafia",
  "division": "Metro Manila",
  "yearJoined": "2019",
  "accomplishments": null,
  "description": null,
  "facebook": "https://www.facebook.com/fliptop.battleleague",
  "twitter": "https://www.x.com/FlipTop_Battles",
  "instagram": "https://www.instagram.com/fliptopbattles",
  "youtube": "https://www.youtube.com/fliptopbattles",
  "latestBattles": [
    {
      "title": "Hazky vs C-Quence",
      "url": null
    },
    {
      "title": "Zaito vs C-Quence vs CNine vs Prince Rhyme vs Castillo",
      "url": null
    },
    {
      "title": "Yuniko vs C-Quence",
      "url": null
    }
  ],
  "metadata": {
    "wins": "",
    "losses": "",
    "rawTextSnippet": "Home\n              Articles\n              Emcees\n              Tournaments\n              Videos\n              Promos\n              Lyrics\n              Tryouts\n              About\n          \n          \n          \n\n            \n               \n               \n               \n               \n               \n            \n\n        \n      \n    \n  \n\n\t\n\n\n\t\t\n\t\t\t\n\t\t\t\t\n\t\t\t\t\t\n\t\t\t\t\t\t\n\t\t\t\t\t\tEmcees\n\t\t\t\t\t\tC-Quence"
  }
}