{
  "name": "pamoso",
  "url": "https://www.fliptop.com.ph/emcees/pamoso",
  "profilePicture": "https://www.fliptop.com.ph/storage/emcees/November2024/5LxhLpA7VafpchPGkx8A.jpg",
  "title": "Emcee: Pamoso | FlipTop Battle League",
  "hometown": "Valenzuela City",
  "reppin": "CPMM, Valuarte",
  "division": "Metro Manila",
  "yearJoined": "2024",
  "accomplishments": null,
  "description": null,
  "facebook": "https://www.facebook.com/kuyapams90",
  "twitter": "https://www.x.com/FlipTop_Battles",
  "instagram": "https://www.instagram.com/fliptopbattles",
  "youtube": "https://www.youtube.com/@KuyaPams",
  "latestBattles": [
    {
      "title": "Pamoso vs BLZR",
      "url": null
    },
    {
      "title": "Pamoso vs Caytriyu",
      "url": null
    },
    {
      "title": "Negho G/Pamoso vs Atoms/Cygnus",
      "url": null
    }
  ],
  "metadata": {
    "wins": "",
    "losses": "",
    "rawTextSnippet": "Home\n              Articles\n              Emcees\n              Tournaments\n              Videos\n              Promos\n              Lyrics\n              Tryouts\n              About\n          \n          \n          \n\n            \n               \n               \n               \n               \n               \n            \n\n        \n      \n    \n  \n\n\t\n\n\n\t\t\n\t\t\t\n\t\t\t\t\n\t\t\t\t\t\n\t\t\t\t\t\t\n\t\t\t\t\t\tEmcees\n\t\t\t\t\t\tPamoso"
  }
}